purldb_toolkit/__init__.py
purldb_toolkit/purlcli.py
purldb_toolkit-0.1.0.dist-info/entry_points.txt
purldb_toolkit-0.1.0.dist-info/WHEEL
purldb_toolkit-0.1.0.dist-info/METADATA
purldb_toolkit-0.1.0.dist-info/NOTICE
purldb_toolkit-0.1.0.dist-info/apache-2.0.LICENSE
purldb_toolkit-0.1.0.dist-info/cc-by-sa-4.0.LICENSE
purldb_toolkit-0.1.0.dist-info/RECORD
